m_calibrate-0.0.3.dist-info/licenses/LICENSE
mcal/__init__.py
mcal/compare.py
mcal/config.py
mcal/criteria.py
mcal/dev.py
mcal/events.py
mcal/local_cluster.py
mcal/new_relic.py
mcal/schedules.py
mcal/actions/__init__.py
mcal/actions/builtin.py
mcal/actions/dask_taxi_cab.py
mcal/actions/db_benchmark.py
mcal/cli/__init__.py
mcal/cli/dev.py
mcal/cli/main.py
mcal/cli/util.py
mcal/dashboard/__init__.py
mcal/dashboard/__main__.py
mcal/dashboard/pages/__init__.py
mcal/dashboard/pages/plot.py
mcal/dashboard/pages/samplers.py
mcal/dashboard/preset/dask_worker.json
mcal/files/__init__.py
mcal/files/config.yml
mcal/files/config_basic_stats.yml
mcal/files/dummy_pod.yml
mcal/files/dummy/my_file.txt
mcal/files/dummy/my_renderable.txt
mcal/files/k8/newrelic-helm-values.yaml
mcal/files/sql/containers_running.sql
mcal/files/sql/pod_top.sql
mcal/runner/__init__.py
mcal/runner/models.py
mcal/runner/orchestrate.py
mcal/samplers/__init__.py
mcal/samplers/base.py
mcal/samplers/dask_k8_cluster.py
mcal/samplers/dask_prom.py
mcal/samplers/dummy.py
mcal/samplers/k8_basic_stats.py
mcal/samplers/kubectl_top.py
mcal/samplers/namespace.py
mcal/samplers/nr_basic_stats.py
mcal/samplers/nr_frequency.py
mcal/samplers/nr_top.py
mcal/samplers/samplers_list.py
mcal/utils/__init__.py
mcal/utils/cmd.py
mcal/utils/env_file.py
mcal/utils/format.py
mcal/utils/logging.py
mcal/utils/nr.py
mcal/utils/pandas.py
mcal/utils/prometheus.py
mcal/utils/shared_model.py
mcal/utils/time.py
mcal/watchers/__init__.py
mcal/watchers/base.py
mcal/watchers/dask.py
mcal/watchers/dummy.py
m_calibrate-0.0.3.dist-info/METADATA
m_calibrate-0.0.3.dist-info/WHEEL
m_calibrate-0.0.3.dist-info/entry_points.txt
m_calibrate-0.0.3.dist-info/top_level.txt
m_calibrate-0.0.3.dist-info/RECORD
