Metadata-Version: 2.4
Name: m-calibrate
Version: 0.0.3
Summary: A multi-purpose calibration tool.
Author: Carter Fendley
License: MIT License
Project-URL: Homepage, https://github.com/CarterFendley/mcal
Classifier: Programming Language :: Python :: 3
Classifier: License :: OSI Approved :: MIT License
Classifier: Operating System :: OS Independent
License-File: LICENSE
Requires-Dist: kubernetes
Requires-Dist: click
Requires-Dist: oyaml
Requires-Dist: jinja2
Requires-Dist: pydantic
Requires-Dist: toml
Requires-Dist: timedelta
Requires-Dist: pandas
Requires-Dist: colorama
Requires-Dist: gql[all]
Provides-Extra: dev
Requires-Dist: pre-commit; extra == "dev"
Requires-Dist: tox; extra == "dev"
Requires-Dist: pytest; extra == "dev"
Requires-Dist: pytest-cov; extra == "dev"
Requires-Dist: pytest-benchmark; extra == "dev"
Requires-Dist: pytest-unordered; extra == "dev"
Provides-Extra: dashboard
Requires-Dist: dash; extra == "dashboard"
Requires-Dist: dash-bootstrap-components; extra == "dashboard"
Provides-Extra: dask
Requires-Dist: dask; extra == "dask"
Requires-Dist: distributed; extra == "dask"
Requires-Dist: dask-kubernetes; extra == "dask"
Requires-Dist: prometheus-client; extra == "dask"
Requires-Dist: pyarrow; extra == "dask"
Requires-Dist: toolz==0.12.0; extra == "dask"
Requires-Dist: lz4==4.3.3; extra == "dask"
Requires-Dist: gcsfs; extra == "dask"
Provides-Extra: docs
Requires-Dist: mkdocs; extra == "docs"
Provides-Extra: all
Requires-Dist: m-calibrate[dask,dev,docs]; extra == "all"
Dynamic: license-file
